feedback_forensics/__init__.py
feedback_forensics/app/__init__.py
feedback_forensics/app/constants.py
feedback_forensics/app/info_texts.py
feedback_forensics/app/interface.py
feedback_forensics/app/main.py
feedback_forensics/app/main_test.py
feedback_forensics/app/metrics.py
feedback_forensics/app/metrics_test.py
feedback_forensics/app/model_annotators.py
feedback_forensics/app/model_annotators_test.py
feedback_forensics/app/styling.py
feedback_forensics/app/url_parser.py
feedback_forensics/app/url_parser_test.py
feedback_forensics/app/utils.py
feedback_forensics/app/callbacks/__init__.py
feedback_forensics/app/callbacks/attach.py
feedback_forensics/app/callbacks/example_viewer.py
feedback_forensics/app/callbacks/loading.py
feedback_forensics/app/callbacks/main.py
feedback_forensics/app/callbacks/update_options.py
feedback_forensics/app/callbacks/utils.py
feedback_forensics/app/plotting/__init__.py
feedback_forensics/app/plotting/constants.py
feedback_forensics/app/plotting/main.py
feedback_forensics/app/plotting/paper.py
feedback_forensics/assets/feedback_forensics_logo.png
feedback_forensics/data/__init__.py
feedback_forensics/data/conftest.py
feedback_forensics/data/dataset_utils.py
feedback_forensics/data/dataset_utils_test.py
feedback_forensics/data/datasets.py
feedback_forensics/data/fetcher.py
feedback_forensics/data/handler.py
feedback_forensics/data/handler_test.py
feedback_forensics/data/loader.py
feedback_forensics/data/loader_test.py
feedback_forensics/data/operations/__init__.py
feedback_forensics/data/operations/core.py
feedback_forensics/data/operations/core_test.py
feedback_forensics/data/operations/merge.py
feedback_forensics/data/operations/merge_test.py
feedback_forensics/tools/__init__.py
feedback_forensics/tools/ff_annotate.py
feedback_forensics/tools/ff_data.py
feedback_forensics/tools/ff_hfspace_rebuild.py
feedback_forensics/tools/ff_model_comparison.py
feedback_forensics/tools/ff_modelgen.py
feedback_forensics-0.4.6.dist-info/METADATA
feedback_forensics-0.4.6.dist-info/WHEEL
feedback_forensics-0.4.6.dist-info/entry_points.txt
feedback_forensics-0.4.6.dist-info/licenses/LICENSE
feedback_forensics-0.4.6.dist-info/RECORD
