Metadata-Version: 2.4
Name: feedback-forensics
Version: 0.4.6
Summary: A tool to investigate your pairwise feedback data
Author-email: rdnfn <hi@arduin.io>, timokau <timo.kaufmann@ifi.lmu.de>
License-File: LICENSE
Classifier: License :: OSI Approved :: Apache Software License
Classifier: Operating System :: OS Independent
Classifier: Programming Language :: Python :: 3
Requires-Python: >=3.10
Requires-Dist: adjusttext
Requires-Dist: alpaca-eval
Requires-Dist: anthropic
Requires-Dist: datasets
Requires-Dist: gradio
Requires-Dist: hydra-core
Requires-Dist: ijson
Requires-Dist: inverse-cai
Requires-Dist: ipywidgets
Requires-Dist: jupyter
Requires-Dist: langchain
Requires-Dist: langchain-anthropic
Requires-Dist: langchain-community
Requires-Dist: langchain-openai
Requires-Dist: loguru
Requires-Dist: msgspec
Requires-Dist: nbconvert
Requires-Dist: pandas
Requires-Dist: python-dotenv
Requires-Dist: scikit-learn
Requires-Dist: wandb
Provides-Extra: dev
Requires-Dist: black==24.10.0; extra == 'dev'
Requires-Dist: bump-my-version; extra == 'dev'
Requires-Dist: huggingface-hub; extra == 'dev'
Requires-Dist: pytest>=6.0; extra == 'dev'
Provides-Extra: docs
Requires-Dist: jupyter-book>=0.15.1; extra == 'docs'
Requires-Dist: myst-parser>=0.18.0; extra == 'docs'
Requires-Dist: sphinx-autodoc2; extra == 'docs'
Requires-Dist: sphinx-book-theme>=1.0.0; extra == 'docs'
Requires-Dist: sphinx-copybutton; extra == 'docs'
Requires-Dist: sphinx-design; extra == 'docs'
Requires-Dist: sphinx>=4.0.0; extra == 'docs'
Requires-Dist: sphinxcontrib-bibtex; extra == 'docs'
